{
	"configurations" : 
	[
		{
			"directories" : 
			[
				{
					"build" : ".",
					"hasInstallRule" : true,
					"jsonFile" : "directory-.-Debug-1a0357fcc4c257140072.json",
					"minimumCMakeVersion" : 
					{
						"string" : "3.16"
					},
					"projectIndex" : 0,
					"source" : ".",
					"targetIndexes" : 
					[
						0,
						1,
						2,
						3,
						4,
						5,
						6,
						7,
						8,
						9,
						10,
						11,
						12,
						13,
						14,
						15
					]
				}
			],
			"name" : "Debug",
			"projects" : 
			[
				{
					"directoryIndexes" : 
					[
						0
					],
					"name" : "swarm_gcs",
					"targetIndexes" : 
					[
						0,
						1,
						2,
						3,
						4,
						5,
						6,
						7,
						8,
						9,
						10,
						11,
						12,
						13,
						14,
						15
					]
				}
			],
			"targets" : 
			[
				{
					"directoryIndex" : 0,
					"id" : "all_aotstats::@6890427a1f51a3e7e1df",
					"jsonFile" : "target-all_aotstats-Debug-00390ba925582c779385.json",
					"name" : "all_aotstats",
					"projectIndex" : 0
				},
				{
					"directoryIndex" : 0,
					"id" : "all_qmllint::@6890427a1f51a3e7e1df",
					"jsonFile" : "target-all_qmllint-Debug-4b9b4b65962201020744.json",
					"name" : "all_qmllint",
					"projectIndex" : 0
				},
				{
					"directoryIndex" : 0,
					"id" : "all_qmllint_json::@6890427a1f51a3e7e1df",
					"jsonFile" : "target-all_qmllint_json-Debug-642ebf177e30a06b9eb6.json",
					"name" : "all_qmllint_json",
					"projectIndex" : 0
				},
				{
					"directoryIndex" : 0,
					"id" : "all_qmllint_module::@6890427a1f51a3e7e1df",
					"jsonFile" : "target-all_qmllint_module-Debug-3f32b9d2a599ad676622.json",
					"name" : "all_qmllint_module",
					"projectIndex" : 0
				},
				{
					"directoryIndex" : 0,
					"id" : "all_qmltyperegistrations::@6890427a1f51a3e7e1df",
					"jsonFile" : "target-all_qmltyperegistrations-Debug-e481408f8881d2544b01.json",
					"name" : "all_qmltyperegistrations",
					"projectIndex" : 0
				},
				{
					"directoryIndex" : 0,
					"id" : "appswarm_gcs::@6890427a1f51a3e7e1df",
					"jsonFile" : "target-appswarm_gcs-Debug-8a2f3381731afa644d14.json",
					"name" : "appswarm_gcs",
					"projectIndex" : 0
				},
				{
					"directoryIndex" : 0,
					"id" : "appswarm_gcs_autogen::@6890427a1f51a3e7e1df",
					"jsonFile" : "target-appswarm_gcs_autogen-Debug-cf9757ba451ca556944e.json",
					"name" : "appswarm_gcs_autogen",
					"projectIndex" : 0
				},
				{
					"directoryIndex" : 0,
					"id" : "appswarm_gcs_autogen_timestamp_deps::@6890427a1f51a3e7e1df",
					"jsonFile" : "target-appswarm_gcs_autogen_timestamp_deps-Debug-4dc79c9f386fe27bc6c1.json",
					"name" : "appswarm_gcs_autogen_timestamp_deps",
					"projectIndex" : 0
				},
				{
					"directoryIndex" : 0,
					"id" : "appswarm_gcs_copy_qml::@6890427a1f51a3e7e1df",
					"jsonFile" : "target-appswarm_gcs_copy_qml-Debug-169b5fa12dedbd7965e6.json",
					"name" : "appswarm_gcs_copy_qml",
					"projectIndex" : 0
				},
				{
					"directoryIndex" : 0,
					"id" : "appswarm_gcs_copy_res::@6890427a1f51a3e7e1df",
					"jsonFile" : "target-appswarm_gcs_copy_res-Debug-6ed2c5896f48c1069e3a.json",
					"name" : "appswarm_gcs_copy_res",
					"projectIndex" : 0
				},
				{
					"directoryIndex" : 0,
					"id" : "appswarm_gcs_qmlimportscan::@6890427a1f51a3e7e1df",
					"jsonFile" : "target-appswarm_gcs_qmlimportscan-Debug-4051ce9457816d45b234.json",
					"name" : "appswarm_gcs_qmlimportscan",
					"projectIndex" : 0
				},
				{
					"directoryIndex" : 0,
					"id" : "appswarm_gcs_qmllint::@6890427a1f51a3e7e1df",
					"jsonFile" : "target-appswarm_gcs_qmllint-Debug-90ce9090f30db463bbbb.json",
					"name" : "appswarm_gcs_qmllint",
					"projectIndex" : 0
				},
				{
					"directoryIndex" : 0,
					"id" : "appswarm_gcs_qmllint_json::@6890427a1f51a3e7e1df",
					"jsonFile" : "target-appswarm_gcs_qmllint_json-Debug-258f42ffa9e1407a5d26.json",
					"name" : "appswarm_gcs_qmllint_json",
					"projectIndex" : 0
				},
				{
					"directoryIndex" : 0,
					"id" : "appswarm_gcs_qmllint_module::@6890427a1f51a3e7e1df",
					"jsonFile" : "target-appswarm_gcs_qmllint_module-Debug-45db06da07d1fa8269a9.json",
					"name" : "appswarm_gcs_qmllint_module",
					"projectIndex" : 0
				},
				{
					"directoryIndex" : 0,
					"id" : "appswarm_gcs_qmltyperegistration::@6890427a1f51a3e7e1df",
					"jsonFile" : "target-appswarm_gcs_qmltyperegistration-Debug-896c792638586183092e.json",
					"name" : "appswarm_gcs_qmltyperegistration",
					"projectIndex" : 0
				},
				{
					"directoryIndex" : 0,
					"id" : "module_appswarm_gcs_aotstats_target::@6890427a1f51a3e7e1df",
					"jsonFile" : "target-module_appswarm_gcs_aotstats_target-Debug-232b2416db7b68d682a5.json",
					"name" : "module_appswarm_gcs_aotstats_target",
					"projectIndex" : 0
				}
			]
		}
	],
	"kind" : "codemodel",
	"paths" : 
	{
		"build" : "D:/QT_projects/swarm_gcs/build/Desktop_Qt_6_9_0_MinGW_64_bit-Debug",
		"source" : "D:/QT_projects/swarm_gcs"
	},
	"version" : 
	{
		"major" : 2,
		"minor" : 7
	}
}
